{
    "1996": [
        {
            "Position": "1",
            "Team": "https://www.transfermarkt.com/vasco-da-gama-rio-de-janeiro/spielplan/verein/978/saison_id/1996",
            "Name": "Vasco da Gama",
            "Matches": "33",
            "Wins": "21",
            "Draws": "7",
            "Losses": "5",
            "Goals": "69:37",
            "Goal Difference": "32",
            "Points": "70"
        },
        {
            "Position": "2",
            "Team": "https://www.transfermarkt.com/se-palmeiras-sao-paulo/spielplan/verein/1023/saison_id/1996",
            "Name": "Palmeiras",
            "Matches": "33",
            "Wins": "15",
            "Draws": "13",
            "Losses": "5",
            "Goals": "57:28",
            "Goal Difference": "29",
            "Points": "58"
        },
        {
            "Position": "3",
            "Team": "https://www.transfermarkt.com/sc-internacional-porto-alegre/spielplan/verein/6600/saison_id/1996",
            "Name": "Internacional",
            "Matches": "31",
            "Wins": "17",
            "Draws": "6",
            "Losses": "8",
            "Goals": "60:31",
            "Goal Difference": "29",
            "Points": "57"
        },
        {
            "Position": "4",
            "Team": "https://www.transfermarkt.com/clube-atletico-mineiro/spielplan/verein/330/saison_id/1996",
            "Name": "Atl\u00e9tico-MG",
            "Matches": "31",
            "Wins": "16",
            "Draws": "5",
            "Losses": "10",
            "Goals": "48:42",
            "Goal Difference": "6",
            "Points": "53"
        },
        {
            "Position": "5",
            "Team": "https://www.transfermarkt.com/flamengo-rio-de-janeiro/spielplan/verein/614/saison_id/1996",
            "Name": "Flamengo",
            "Matches": "31",
            "Wins": "14",
            "Draws": "8",
            "Losses": "9",
            "Goals": "37:32",
            "Goal Difference": "5",
            "Points": "50"
        },
        {
            "Position": "6",
            "Team": "https://www.transfermarkt.com/portuguesa-sao-paulo/spielplan/verein/10247/saison_id/1996",
            "Name": "Portuguesa",
            "Matches": "31",
            "Wins": "13",
            "Draws": "10",
            "Losses": "8",
            "Goals": "50:36",
            "Goal Difference": "14",
            "Points": "49"
        },
        {
            "Position": "7",
            "Team": "https://www.transfermarkt.com/fc-santos/spielplan/verein/221/saison_id/1996",
            "Name": "Santos",
            "Matches": "31",
            "Wins": "14",
            "Draws": "6",
            "Losses": "11",
            "Goals": "48:43",
            "Goal Difference": "5",
            "Points": "48"
        },
        {
            "Position": "8",
            "Team": "https://www.transfermarkt.com/esporte-clube-juventude/spielplan/verein/10492/saison_id/1996",
            "Name": "Juventude",
            "Matches": "31",
            "Wins": "11",
            "Draws": "11",
            "Losses": "9",
            "Goals": "30:31",
            "Goal Difference": "-1",
            "Points": "44"
        },
        {
            "Position": "9",
            "Team": "https://www.transfermarkt.com/esporte-clube-vitoria/spielplan/verein/2125/saison_id/1996",
            "Name": "EC Vit\u00f3ria",
            "Matches": "25",
            "Wins": "9",
            "Draws": "9",
            "Losses": "7",
            "Goals": "44:40",
            "Goal Difference": "4",
            "Points": "36"
        },
        {
            "Position": "10",
            "Team": "https://www.transfermarkt.com/botafogo-rio-de-janeiro/spielplan/verein/537/saison_id/1996",
            "Name": "Botafogo",
            "Matches": "25",
            "Wins": "8",
            "Draws": "10",
            "Losses": "7",
            "Goals": "32:32",
            "Goal Difference": "0",
            "Points": "34"
        },
        {
            "Position": "11",
            "Team": "https://www.transfermarkt.com/fc-sao-paulo/spielplan/verein/585/saison_id/1996",
            "Name": "S\u00e3o Paulo",
            "Matches": "25",
            "Wins": "8",
            "Draws": "9",
            "Losses": "8",
            "Goals": "41:32",
            "Goal Difference": "9",
            "Points": "33"
        },
        {
            "Position": "12",
            "Team": "https://www.transfermarkt.com/sport-club-do-recife/spielplan/verein/8718/saison_id/1996",
            "Name": "Sport Recife",
            "Matches": "25",
            "Wins": "9",
            "Draws": "6",
            "Losses": "10",
            "Goals": "34:32",
            "Goal Difference": "2",
            "Points": "33"
        },
        {
            "Position": "13",
            "Team": "https://www.transfermarkt.com/club-athletico-paranaense/spielplan/verein/679/saison_id/1996",
            "Name": "Atl\u00e9tico-PR",
            "Matches": "25",
            "Wins": "9",
            "Draws": "6",
            "Losses": "10",
            "Goals": "37:41",
            "Goal Difference": "-4",
            "Points": "33"
        },
        {
            "Position": "14",
            "Team": "https://www.transfermarkt.com/parana-clube/spielplan/verein/309/saison_id/1996",
            "Name": "Paran\u00e1",
            "Matches": "25",
            "Wins": "8",
            "Draws": "8",
            "Losses": "9",
            "Goals": "30:30",
            "Goal Difference": "0",
            "Points": "32"
        },
        {
            "Position": "15",
            "Team": "https://www.transfermarkt.com/gremio-porto-alegre/spielplan/verein/210/saison_id/1996",
            "Name": "Gr\u00eamio",
            "Matches": "25",
            "Wins": "7",
            "Draws": "10",
            "Losses": "8",
            "Goals": "34:47",
            "Goal Difference": "-13",
            "Points": "31"
        },
        {
            "Position": "16",
            "Team": "https://www.transfermarkt.com/coritiba-fc/spielplan/verein/776/saison_id/1996",
            "Name": "Coritiba FC",
            "Matches": "25",
            "Wins": "7",
            "Draws": "9",
            "Losses": "9",
            "Goals": "31:32",
            "Goal Difference": "-1",
            "Points": "30"
        },
        {
            "Position": "17",
            "Team": "https://www.transfermarkt.com/america-futebol-clube-rn-/spielplan/verein/1751/saison_id/1996",
            "Name": "Am\u00e9rica-RN",
            "Matches": "25",
            "Wins": "7",
            "Draws": "9",
            "Losses": "9",
            "Goals": "31:40",
            "Goal Difference": "-9",
            "Points": "30"
        },
        {
            "Position": "18",
            "Team": "https://www.transfermarkt.com/corinthians-sao-paulo/spielplan/verein/199/saison_id/1996",
            "Name": "Corinthians",
            "Matches": "25",
            "Wins": "8",
            "Draws": "5",
            "Losses": "12",
            "Goals": "23:27",
            "Goal Difference": "-4",
            "Points": "29"
        },
        {
            "Position": "19",
            "Team": "https://www.transfermarkt.com/ec-cruzeiro-belo-horizonte/spielplan/verein/609/saison_id/1996",
            "Name": "Cruzeiro",
            "Matches": "25",
            "Wins": "6",
            "Draws": "10",
            "Losses": "9",
            "Goals": "30:35",
            "Goal Difference": "-5",
            "Points": "28"
        },
        {
            "Position": "20",
            "Team": "https://www.transfermarkt.com/guarani-fc-sp-/spielplan/verein/1755/saison_id/1996",
            "Name": "Guarani",
            "Matches": "25",
            "Wins": "6",
            "Draws": "10",
            "Losses": "9",
            "Goals": "36:43",
            "Goal Difference": "-7",
            "Points": "28"
        },
        {
            "Position": "21",
            "Team": "https://www.transfermarkt.com/goias-ec/spielplan/verein/3197/saison_id/1996",
            "Name": "Goi\u00e1s",
            "Matches": "25",
            "Wins": "8",
            "Draws": "4",
            "Losses": "13",
            "Goals": "30:40",
            "Goal Difference": "-10",
            "Points": "28"
        },
        {
            "Position": "22",
            "Team": "https://www.transfermarkt.com/esporte-clube-bahia/spielplan/verein/10010/saison_id/1996",
            "Name": "EC Bahia",
            "Matches": "25",
            "Wins": "6",
            "Draws": "8",
            "Losses": "11",
            "Goals": "39:49",
            "Goal Difference": "-10",
            "Points": "26"
        },
        {
            "Position": "23",
            "Team": "https://www.transfermarkt.com/red-bull-bragantino/spielplan/verein/8793/saison_id/1996",
            "Name": "Bragantino",
            "Matches": "25",
            "Wins": "7",
            "Draws": "5",
            "Losses": "13",
            "Goals": "27:46",
            "Goal Difference": "-19",
            "Points": "26"
        },
        {
            "Position": "24",
            "Team": "https://www.transfermarkt.com/criciuma-esporte-clube/spielplan/verein/7178/saison_id/1996",
            "Name": "Crici\u00fama EC",
            "Matches": "25",
            "Wins": "6",
            "Draws": "7",
            "Losses": "12",
            "Goals": "27:35",
            "Goal Difference": "-8",
            "Points": "25"
        },
        {
            "Position": "25",
            "Team": "https://www.transfermarkt.com/fluminense-rio-de-janeiro/spielplan/verein/2462/saison_id/1996",
            "Name": "Fluminense",
            "Matches": "25",
            "Wins": "4",
            "Draws": "10",
            "Losses": "11",
            "Goals": "26:41",
            "Goal Difference": "-15",
            "Points": "22"
        },
        {
            "Position": "26",
            "Team": "https://www.transfermarkt.com/uniao-sao-joao-esporte-clube-sp-/spielplan/verein/734/saison_id/1996",
            "Name": "Uni\u00e3o S\u00e3o Jo\u00e3o",
            "Matches": "25",
            "Wins": "2",
            "Draws": "9",
            "Losses": "14",
            "Goals": "18:47",
            "Goal Difference": "-29",
            "Points": "15"
        }
    ],
    "1997": [
        {
            "Position": "1",
            "Team": "https://www.transfermarkt.com/corinthians-sao-paulo/spielplan/verein/199/saison_id/1997",
            "Name": "Corinthians",
            "Matches": "32",
            "Wins": "18",
            "Draws": "7",
            "Losses": "7",
            "Goals": "57:38",
            "Goal Difference": "19",
            "Points": "61"
        },
        {
            "Position": "2",
            "Team": "https://www.transfermarkt.com/fc-santos/spielplan/verein/221/saison_id/1997",
            "Name": "Santos",
            "Matches": "29",
            "Wins": "14",
            "Draws": "9",
            "Losses": "6",
            "Goals": "55:36",
            "Goal Difference": "19",
            "Points": "51"
        },
        {
            "Position": "3",
            "Team": "https://www.transfermarkt.com/ec-cruzeiro-belo-horizonte/spielplan/verein/609/saison_id/1997",
            "Name": "Cruzeiro",
            "Matches": "32",
            "Wins": "14",
            "Draws": "9",
            "Losses": "9",
            "Goals": "56:41",
            "Goal Difference": "15",
            "Points": "51"
        },
        {
            "Position": "4",
            "Team": "https://www.transfermarkt.com/se-palmeiras-sao-paulo/spielplan/verein/1023/saison_id/1997",
            "Name": "Palmeiras",
            "Matches": "26",
            "Wins": "15",
            "Draws": "3",
            "Losses": "8",
            "Goals": "51:38",
            "Goal Difference": "13",
            "Points": "48"
        },
        {
            "Position": "5",
            "Team": "https://www.transfermarkt.com/portuguesa-sao-paulo/spielplan/verein/10247/saison_id/1997",
            "Name": "Portuguesa",
            "Matches": "29",
            "Wins": "13",
            "Draws": "9",
            "Losses": "7",
            "Goals": "52:42",
            "Goal Difference": "10",
            "Points": "48"
        },
        {
            "Position": "6",
            "Team": "https://www.transfermarkt.com/coritiba-fc/spielplan/verein/776/saison_id/1997",
            "Name": "Coritiba FC",
            "Matches": "26",
            "Wins": "11",
            "Draws": "11",
            "Losses": "4",
            "Goals": "35:31",
            "Goal Difference": "4",
            "Points": "44"
        },
        {
            "Position": "7",
            "Team": "https://www.transfermarkt.com/sport-club-do-recife/spielplan/verein/8718/saison_id/1997",
            "Name": "Sport Recife",
            "Matches": "26",
            "Wins": "13",
            "Draws": "4",
            "Losses": "9",
            "Goals": "38:28",
            "Goal Difference": "10",
            "Points": "43"
        },
        {
            "Position": "8",
            "Team": "https://www.transfermarkt.com/gremio-porto-alegre/spielplan/verein/210/saison_id/1997",
            "Name": "Gr\u00eamio",
            "Matches": "26",
            "Wins": "11",
            "Draws": "6",
            "Losses": "9",
            "Goals": "34:32",
            "Goal Difference": "2",
            "Points": "39"
        },
        {
            "Position": "9",
            "Team": "https://www.transfermarkt.com/clube-atletico-mineiro/spielplan/verein/330/saison_id/1997",
            "Name": "Atl\u00e9tico-MG",
            "Matches": "23",
            "Wins": "9",
            "Draws": "9",
            "Losses": "5",
            "Goals": "38:33",
            "Goal Difference": "5",
            "Points": "36"
        },
        {
            "Position": "10",
            "Team": "https://www.transfermarkt.com/vasco-da-gama-rio-de-janeiro/spielplan/verein/978/saison_id/1997",
            "Name": "Vasco da Gama",
            "Matches": "23",
            "Wins": "9",
            "Draws": "7",
            "Losses": "7",
            "Goals": "34:24",
            "Goal Difference": "10",
            "Points": "34"
        },
        {
            "Position": "11",
            "Team": "https://www.transfermarkt.com/flamengo-rio-de-janeiro/spielplan/verein/614/saison_id/1997",
            "Name": "Flamengo",
            "Matches": "23",
            "Wins": "9",
            "Draws": "6",
            "Losses": "8",
            "Goals": "37:34",
            "Goal Difference": "3",
            "Points": "33"
        },
        {
            "Position": "12",
            "Team": "https://www.transfermarkt.com/sc-internacional-porto-alegre/spielplan/verein/6600/saison_id/1997",
            "Name": "Internacional",
            "Matches": "23",
            "Wins": "9",
            "Draws": "5",
            "Losses": "9",
            "Goals": "25:25",
            "Goal Difference": "0",
            "Points": "32"
        },
        {
            "Position": "13",
            "Team": "https://www.transfermarkt.com/esporte-clube-vitoria/spielplan/verein/2125/saison_id/1997",
            "Name": "EC Vit\u00f3ria",
            "Matches": "23",
            "Wins": "9",
            "Draws": "3",
            "Losses": "11",
            "Goals": "31:38",
            "Goal Difference": "-7",
            "Points": "30"
        },
        {
            "Position": "14",
            "Team": "https://www.transfermarkt.com/botafogo-rio-de-janeiro/spielplan/verein/537/saison_id/1997",
            "Name": "Botafogo",
            "Matches": "23",
            "Wins": "7",
            "Draws": "8",
            "Losses": "8",
            "Goals": "35:37",
            "Goal Difference": "-2",
            "Points": "29"
        },
        {
            "Position": "15",
            "Team": "https://www.transfermarkt.com/club-athletico-paranaense/spielplan/verein/679/saison_id/1997",
            "Name": "Atl\u00e9tico-PR",
            "Matches": "23",
            "Wins": "7",
            "Draws": "6",
            "Losses": "10",
            "Goals": "32:32",
            "Goal Difference": "0",
            "Points": "27"
        },
        {
            "Position": "16",
            "Team": "https://www.transfermarkt.com/fc-sao-paulo/spielplan/verein/585/saison_id/1997",
            "Name": "S\u00e3o Paulo",
            "Matches": "23",
            "Wins": "8",
            "Draws": "3",
            "Losses": "12",
            "Goals": "34:35",
            "Goal Difference": "-1",
            "Points": "27"
        },
        {
            "Position": "17",
            "Team": "https://www.transfermarkt.com/aa-ponte-preta/spielplan/verein/1134/saison_id/1997",
            "Name": "Ponte Preta",
            "Matches": "23",
            "Wins": "7",
            "Draws": "5",
            "Losses": "11",
            "Goals": "25:34",
            "Goal Difference": "-9",
            "Points": "26"
        },
        {
            "Position": "18",
            "Team": "https://www.transfermarkt.com/esporte-clube-juventude/spielplan/verein/10492/saison_id/1997",
            "Name": "Juventude",
            "Matches": "23",
            "Wins": "6",
            "Draws": "8",
            "Losses": "9",
            "Goals": "23:32",
            "Goal Difference": "-9",
            "Points": "26"
        },
        {
            "Position": "19",
            "Team": "https://www.transfermarkt.com/guarani-fc-sp-/spielplan/verein/1755/saison_id/1997",
            "Name": "Guarani",
            "Matches": "23",
            "Wins": "6",
            "Draws": "7",
            "Losses": "10",
            "Goals": "34:39",
            "Goal Difference": "-5",
            "Points": "25"
        },
        {
            "Position": "20",
            "Team": "https://www.transfermarkt.com/parana-clube/spielplan/verein/309/saison_id/1997",
            "Name": "Paran\u00e1",
            "Matches": "23",
            "Wins": "7",
            "Draws": "3",
            "Losses": "13",
            "Goals": "25:41",
            "Goal Difference": "-16",
            "Points": "24"
        },
        {
            "Position": "21",
            "Team": "https://www.transfermarkt.com/america-futebol-clube-mg-/spielplan/verein/2863/saison_id/1997",
            "Name": "Am\u00e9rica-MG",
            "Matches": "23",
            "Wins": "6",
            "Draws": "5",
            "Losses": "12",
            "Goals": "26:39",
            "Goal Difference": "-13",
            "Points": "23"
        },
        {
            "Position": "22",
            "Team": "https://www.transfermarkt.com/goias-ec/spielplan/verein/3197/saison_id/1997",
            "Name": "Goi\u00e1s",
            "Matches": "23",
            "Wins": "5",
            "Draws": "7",
            "Losses": "11",
            "Goals": "29:37",
            "Goal Difference": "-8",
            "Points": "22"
        },
        {
            "Position": "23",
            "Team": "https://www.transfermarkt.com/red-bull-bragantino/spielplan/verein/8793/saison_id/1997",
            "Name": "Bragantino",
            "Matches": "23",
            "Wins": "5",
            "Draws": "6",
            "Losses": "12",
            "Goals": "20:37",
            "Goal Difference": "-17",
            "Points": "21"
        },
        {
            "Position": "24",
            "Team": "https://www.transfermarkt.com/america-futebol-clube-rn-/spielplan/verein/1751/saison_id/1997",
            "Name": "Am\u00e9rica-RN",
            "Matches": "23",
            "Wins": "3",
            "Draws": "6",
            "Losses": "14",
            "Goals": "24:47",
            "Goal Difference": "-23",
            "Points": "15"
        }
    ]
}